pyccs-1.1.0.dist-info/RECORD
pyccs-1.1.0.dist-info/METADATA
pyccs-1.1.0.dist-info/WHEEL
pyccs/_ccs.py
pyccs/pyccs.cpython-37m-x86_64-linux-gnu.so
pyccs/__init__.py
