Metadata-Version: 2.1
Name: pyccs
Version: 1.1.0
Author: Jinyang Zhang <zhangjinyang@biols.ac.cn
Author-email: Jinyang Zhang <zhangjinyang@biols.ac.cn
Maintainer: Jinyang Zhang
Maintainer-email: zhangjinyang@biols.ac.cn
Requires-Python: >=3.7
Project-URL: homepage, https://github.com/Kevinzjy/pyccs
